mistrasdta_hdf5/__init__.py
mistrasdta_hdf5/constants.py
mistrasdta_hdf5/hdf5.py
mistrasdta_hdf5/stream.py
mistrasdta_hdf5-0.1.6.dist-info/licenses/LICENSE.txt
mistrasdta_hdf5-0.1.6.dist-info/METADATA
mistrasdta_hdf5-0.1.6.dist-info/WHEEL
mistrasdta_hdf5-0.1.6.dist-info/top_level.txt
mistrasdta_hdf5-0.1.6.dist-info/RECORD
