Metadata-Version: 2.4
Name: mistrasdta-hdf5
Version: 0.1.6
Summary: Streaming parser and HDF5 exporter for Mistras DTA acoustic emission data
Author: Robert Farla
Maintainer: Robert Farla
License-Expression: MIT
Project-URL: Homepage, https://github.com/<your-username>/MistrasDTA-hdf5
Project-URL: Repository, https://github.com/<your-username>/MistrasDTA-hdf5
Project-URL: Issues, https://github.com/<your-username>/MistrasDTA-hdf5/issues
Keywords: acoustic-emission,mistras,dta,hdf5,streaming,scientific-data
Classifier: Development Status :: 3 - Alpha
Classifier: Intended Audience :: Science/Research
Classifier: Operating System :: OS Independent
Classifier: Programming Language :: Python :: 3
Classifier: Programming Language :: Python :: 3.9
Classifier: Programming Language :: Python :: 3.10
Classifier: Programming Language :: Python :: 3.11
Classifier: Topic :: Scientific/Engineering :: Physics
Classifier: Topic :: Scientific/Engineering :: Information Analysis
Requires-Python: >=3.9
License-File: LICENSE.txt
Requires-Dist: numpy>=1.22
Provides-Extra: hdf5
Requires-Dist: h5py>=3.9; extra == "hdf5"
Dynamic: license-file
